tmdbfusion/__init__.py
tmdbfusion/exceptions.py
tmdbfusion/api/__init__.py
tmdbfusion/api/_base.py
tmdbfusion/api/account.py
tmdbfusion/api/account_v4.py
tmdbfusion/api/auth_v4.py
tmdbfusion/api/authentication.py
tmdbfusion/api/certifications.py
tmdbfusion/api/changes.py
tmdbfusion/api/collections.py
tmdbfusion/api/companies.py
tmdbfusion/api/configuration.py
tmdbfusion/api/credits.py
tmdbfusion/api/discover.py
tmdbfusion/api/find.py
tmdbfusion/api/genres.py
tmdbfusion/api/guest_session.py
tmdbfusion/api/keywords.py
tmdbfusion/api/lists.py
tmdbfusion/api/lists_v4.py
tmdbfusion/api/movies.py
tmdbfusion/api/networks.py
tmdbfusion/api/people.py
tmdbfusion/api/reviews.py
tmdbfusion/api/search.py
tmdbfusion/api/trending.py
tmdbfusion/api/tv.py
tmdbfusion/api/tv_episode_groups.py
tmdbfusion/api/tv_episodes.py
tmdbfusion/api/tv_seasons.py
tmdbfusion/api/watch_providers.py
tmdbfusion/cli/__init__.py
tmdbfusion/cli/commands.py
tmdbfusion/cli/console.py
tmdbfusion/core/__init__.py
tmdbfusion/core/async_client.py
tmdbfusion/core/base.py
tmdbfusion/core/cache.py
tmdbfusion/core/client.py
tmdbfusion/core/http.py
tmdbfusion/core/sync_client.py
tmdbfusion/data/__init__.py
tmdbfusion/data/dataset.py
tmdbfusion/data/download.py
tmdbfusion/data/export.py
tmdbfusion/data/sync.py
tmdbfusion/features/__init__.py
tmdbfusion/features/batch.py
tmdbfusion/features/bulk.py
tmdbfusion/features/pagination.py
tmdbfusion/features/rate_limit.py
tmdbfusion/models/__init__.py
tmdbfusion/models/account.py
tmdbfusion/models/common.py
tmdbfusion/models/movie.py
tmdbfusion/models/person.py
tmdbfusion/models/responses.py
tmdbfusion/models/responses_extra.py
tmdbfusion/models/search.py
tmdbfusion/models/tv.py
tmdbfusion/utils/__init__.py
tmdbfusion/utils/append.py
tmdbfusion/utils/detect.py
tmdbfusion/utils/discover.py
tmdbfusion/utils/helpers.py
tmdbfusion/utils/images.py
tmdbfusion/utils/links.py
tmdbfusion/utils/navigator.py
tmdbfusion/utils/presets.py
tmdbfusion/utils/watcher.py
tmdbfusion-0.2.0.dist-info/METADATA
tmdbfusion-0.2.0.dist-info/WHEEL
tmdbfusion-0.2.0.dist-info/entry_points.txt
tmdbfusion-0.2.0.dist-info/licenses/LICENSE
tmdbfusion-0.2.0.dist-info/RECORD
