Metadata-Version: 2.4
Name: tmdbfusion
Version: 0.2.0
Summary: Simple, high-performance Python wrapper for The Movie Database API
Author: xsyncio
License-File: LICENSE
Requires-Python: >=3.13
Requires-Dist: httpx>=0.24.1
Requires-Dist: msgspec>=0.18.0
Provides-Extra: cli
Requires-Dist: click>=8.1.0; extra == 'cli'
Requires-Dist: rich>=13.0.0; extra == 'cli'
Provides-Extra: dev
Requires-Dist: bump-my-version>=0.10.0; extra == 'dev'
Requires-Dist: deptry>=0.12.0; extra == 'dev'
Requires-Dist: mypy>=1.4.1; extra == 'dev'
Requires-Dist: nox>=2023.4.22; extra == 'dev'
Requires-Dist: numpydoc>=1.6.0; extra == 'dev'
Requires-Dist: pip-audit>=2.5.6; extra == 'dev'
Requires-Dist: pre-commit>=3.3.3; extra == 'dev'
Requires-Dist: pytest-asyncio>=1.3.0; extra == 'dev'
Requires-Dist: pytest-cov>=4.1.0; extra == 'dev'
Requires-Dist: pytest>=7.4.0; extra == 'dev'
Requires-Dist: respx>=0.22.0; extra == 'dev'
Requires-Dist: ruff>=0.0.278; extra == 'dev'
Requires-Dist: towncrier>=23.6.0; extra == 'dev'
Provides-Extra: docs
Requires-Dist: mkdocs-awesome-pages-plugin>=2.9.0; extra == 'docs'
Requires-Dist: mkdocs-git-authors-plugin>=0.7.0; extra == 'docs'
Requires-Dist: mkdocs-git-revision-date-localized-plugin>=1.2.0; extra == 'docs'
Requires-Dist: mkdocs-glightbox>=0.3.0; extra == 'docs'
Requires-Dist: mkdocs-macros-plugin>=1.0.0; extra == 'docs'
Requires-Dist: mkdocs-material>=9.5.0; extra == 'docs'
Requires-Dist: mkdocs-mermaid2-plugin>=1.1.0; extra == 'docs'
Requires-Dist: mkdocs-minify-plugin>=0.7.0; extra == 'docs'
Requires-Dist: mkdocs-rss-plugin>=1.9.0; extra == 'docs'
Requires-Dist: mkdocs-section-index>=0.3.0; extra == 'docs'
Requires-Dist: mkdocstrings[python]>=0.24.0; extra == 'docs'
Requires-Dist: pymdown-extensions>=10.7.0; extra == 'docs'
Provides-Extra: rich
Requires-Dist: rich>=13.0.0; extra == 'rich'
